mlens/__init__.py
mlens/config.py
mlens/ensemble/__init__.py
mlens/ensemble/base.py
mlens/ensemble/blend.py
mlens/ensemble/sequential.py
mlens/ensemble/subsemble.py
mlens/ensemble/super_learner.py
mlens/ensemble/temporal.py
mlens/estimators/__init__.py
mlens/estimators/estimators.py
mlens/externals/__init__.py
mlens/externals/fixes.py
mlens/externals/funcsigs.py
mlens/externals/six.py
mlens/externals/joblib/__init__.py
mlens/externals/joblib/_compat.py
mlens/externals/joblib/_memory_helpers.py
mlens/externals/joblib/_multiprocessing_helpers.py
mlens/externals/joblib/_parallel_backends.py
mlens/externals/joblib/backports.py
mlens/externals/joblib/disk.py
mlens/externals/joblib/format_stack.py
mlens/externals/joblib/func_inspect.py
mlens/externals/joblib/hashing.py
mlens/externals/joblib/logger.py
mlens/externals/joblib/memory.py
mlens/externals/joblib/my_exceptions.py
mlens/externals/joblib/numpy_pickle.py
mlens/externals/joblib/numpy_pickle_compat.py
mlens/externals/joblib/numpy_pickle_utils.py
mlens/externals/joblib/parallel.py
mlens/externals/joblib/pool.py
mlens/externals/sklearn/__init__.py
mlens/externals/sklearn/base.py
mlens/externals/sklearn/exceptions.py
mlens/externals/sklearn/scorer.py
mlens/externals/sklearn/type_of_target.py
mlens/externals/sklearn/validation.py
mlens/index/__init__.py
mlens/index/_checks.py
mlens/index/base.py
mlens/index/blend.py
mlens/index/fold.py
mlens/index/subsemble.py
mlens/index/temporal.py
mlens/metrics/__init__.py
mlens/metrics/metrics.py
mlens/metrics/utils.py
mlens/model_selection/__init__.py
mlens/model_selection/_base_functions.py
mlens/model_selection/model_selection.py
mlens/parallel/__init__.py
mlens/parallel/_base_functions.py
mlens/parallel/backend.py
mlens/parallel/base.py
mlens/parallel/handles.py
mlens/parallel/layer.py
mlens/parallel/learner.py
mlens/parallel/wrapper.py
mlens/preprocessing/__init__.py
mlens/preprocessing/preprocess.py
mlens-0.2.3.dist-info/METADATA
mlens-0.2.3.dist-info/RECORD
mlens-0.2.3.dist-info/WHEEL
mlens-0.2.3.dist-info/top_level.txt
