Metadata-Version: 1.1
Name: mlens
Version: 0.2.3
Summary: Machine Learning Ensemble Library
Home-page: https://github.com/flennerhag/mlens
Author: Sebastian Flennerhag
Author-email: sebastianflennerhag@hotmail.com
License: MIT
Platform: any
Classifier: License :: OSI Approved :: MIT License
Classifier: Development Status :: 4 - Beta
Classifier: Operating System :: Microsoft :: Windows
Classifier: Operating System :: POSIX
Classifier: Operating System :: Unix
Classifier: Operating System :: MacOS
Classifier: Programming Language :: Python :: 2.7
Classifier: Programming Language :: Python :: 3.5
Classifier: Programming Language :: Python :: 3.6
Classifier: Topic :: Scientific/Engineering
Classifier: Topic :: Scientific/Engineering :: Artificial Intelligence
